json_canonical/Canonicalize.py
json_canonical/NumberToJson.py
json_canonical/__init__.py
json_canonical-2.0.0.dist-info/LICENSE
json_canonical-2.0.0.dist-info/METADATA
json_canonical-2.0.0.dist-info/WHEEL
json_canonical-2.0.0.dist-info/top_level.txt
json_canonical-2.0.0.dist-info/RECORD
