Metadata-Version: 2.1
Name: json-canonical
Version: 2.0.0
Summary: Conanicalize JSON in JCS format
Home-page: https://github.com/AnasMK/json-canonical
Author: Anas Kanhouch
Author-email: anas.m.kan@gmail.com
License: Apache License
Platform: UNKNOWN
